setup.py
appresso_sphinx_extensions/__init__.py
appresso_sphinx_extensions/settings.py
appresso_sphinx_extensions.egg-info/PKG-INFO
appresso_sphinx_extensions.egg-info/SOURCES.txt
appresso_sphinx_extensions.egg-info/dependency_links.txt
appresso_sphinx_extensions.egg-info/pbr.json
appresso_sphinx_extensions.egg-info/requires.txt
appresso_sphinx_extensions.egg-info/top_level.txt
appresso_sphinx_extensions.egg-info/zip-safe