Metadata-Version: 1.1
Name: appresso-sphinx-extensions
Version: 1.0.0
Summary: Sphinx documentation system extensions created by Appresso AS
Home-page: https://github.com/appressoas/appresso_sphinx_extensions
Author: Espen Angell Kristiansen
Author-email: espen@appresso.no
License: BSD
Platform: UNKNOWN
Classifier: Intended Audience :: Developers
Classifier: License :: OSI Approved
Classifier: Programming Language :: Python
